pydcce/__init__.py
pydcce/estimators/__init__.py
pydcce/estimators/base.py
pydcce/estimators/cce.py
pydcce/estimators/csardl.py
pydcce/estimators/csdl.py
pydcce/estimators/ecm.py
pydcce/estimators/mean_group.py
pydcce/estimators/pooled.py
pydcce/estimators/rcce.py
pydcce/output/__init__.py
pydcce/output/tables.py
pydcce/tests/__init__.py
pydcce/tests/cd_test.py
pydcce/tests/exponent.py
pydcce/utils/__init__.py
pydcce/utils/cross_sectional.py
pydcce/utils/matrix.py
pydcce/utils/panel.py
pydcce-1.0.1.dist-info/METADATA
pydcce-1.0.1.dist-info/WHEEL
pydcce-1.0.1.dist-info/top_level.txt
pydcce-1.0.1.dist-info/RECORD
