Metadata-Version: 2.4
Name: pydcce
Version: 1.0.1
Summary: Dynamic Common Correlated Effects Estimation for Panel Data with Cross-Sectional Dependence
Author-email: "Dr. Merwan Roudane" <merwanroudane920@gmail.com>
Maintainer-email: "Dr. Merwan Roudane" <merwanroudane920@gmail.com>
License-Expression: MIT
Project-URL: Homepage, https://github.com/merwanroudane/pydecce2
Project-URL: Documentation, https://github.com/merwanroudane/pydecce2
Project-URL: Repository, https://github.com/merwanroudane/pydecce2
Project-URL: Issues, https://github.com/merwanroudane/pydecce2/issues
Keywords: econometrics,panel-data,cross-sectional-dependence,common-correlated-effects,dynamic-panels,mean-group,pesaran,cd-test,heterogeneous-panels
Classifier: Development Status :: 5 - Production/Stable
Classifier: Intended Audience :: Science/Research
Classifier: Intended Audience :: Education
Classifier: Operating System :: OS Independent
Classifier: Programming Language :: Python :: 3
Classifier: Programming Language :: Python :: 3.8
Classifier: Programming Language :: Python :: 3.9
Classifier: Programming Language :: Python :: 3.10
Classifier: Programming Language :: Python :: 3.11
Classifier: Programming Language :: Python :: 3.12
Classifier: Topic :: Scientific/Engineering :: Mathematics
Classifier: Topic :: Scientific/Engineering :: Information Analysis
Requires-Python: >=3.8
Requires-Dist: numpy>=1.20.0
Requires-Dist: pandas>=1.3.0
Requires-Dist: scipy>=1.7.0
Requires-Dist: statsmodels>=0.13.0
Requires-Dist: tabulate>=0.9.0
Requires-Dist: matplotlib>=3.5.0
Requires-Dist: seaborn>=0.11.0
Provides-Extra: dev
Requires-Dist: pytest>=7.0.0; extra == "dev"
Requires-Dist: pytest-cov>=4.0.0; extra == "dev"
Requires-Dist: black>=23.0.0; extra == "dev"
Requires-Dist: isort>=5.12.0; extra == "dev"
